pylmcf/__init__.py
pylmcf/__main__.py
pylmcf/__version__.py
pylmcf/cpp/lemon/assert.h
pylmcf/cpp/lemon/bits/alteration_notifier.h
pylmcf/cpp/lemon/bits/array_map.h
pylmcf/cpp/lemon/bits/default_map.h
pylmcf/cpp/lemon/bits/enable_if.h
pylmcf/cpp/lemon/bits/graph_extender.h
pylmcf/cpp/lemon/bits/lock.h
pylmcf/cpp/lemon/bits/map_extender.h
pylmcf/cpp/lemon/bits/traits.h
pylmcf/cpp/lemon/bits/vector_map.h
pylmcf/cpp/lemon/bits/windows.cc
pylmcf/cpp/lemon/bits/windows.h
pylmcf/cpp/lemon/concept_check.h
pylmcf/cpp/lemon/concepts/maps.h
pylmcf/cpp/lemon/config.h
pylmcf/cpp/lemon/core.h
pylmcf/cpp/lemon/error.h
pylmcf/cpp/lemon/list_graph.h
pylmcf/cpp/lemon/math.h
pylmcf/cpp/lemon/network_simplex.h
pylmcf/cpp/lemon/static_graph.h
pylmcf/cpp/pylmcf/basics.hpp
pylmcf/cpp/pylmcf/graph.hpp
pylmcf/cpp/pylmcf/lmcf.hpp
pylmcf/cpp/pylmcf/py_support.hpp
pylmcf/cpp/pylmcf/pylmcf.cpp
pylmcf/graph.py
pylmcf/pylmcf_cpp.cp312-win32.pyd
pylmcf-0.9.2.dist-info/METADATA
pylmcf-0.9.2.dist-info/WHEEL
pylmcf-0.9.2.dist-info/licenses/LICENCE
pylmcf-0.9.2.dist-info/RECORD
