Metadata-Version: 2.4
Name: pylmcf
Version: 0.9.2
Summary: Python bindings for Network Simplex algorithm from LEMON library
Keywords: network simplex,minimum cost flow,lemon,graph algorithms
Author-Email: =?utf-8?q?Micha=C5=82_Startek?= <michal.startek@mimuw.edu.pl>
Maintainer-Email: =?utf-8?q?Micha=C5=82_Startek?= <michal.startek@mimuw.edu.pl>
License-Expression: BSL-1.0
License-File: LICENCE
Classifier: Programming Language :: Python :: 3
Classifier: Operating System :: OS Independent
Classifier: Topic :: Scientific/Engineering :: Mathematics
Classifier: Topic :: Software Development :: Libraries :: Python Modules
Classifier: Development Status :: 4 - Beta
Project-URL: Homepage, https://github.com/michalsta/pylmcf
Project-URL: Repository, https://github.com/michalsta/pylmcf.git
Requires-Dist: numpy
Provides-Extra: extras
Requires-Dist: networkx; extra == "extras"
Requires-Dist: matplotlib; extra == "extras"
